pika/__init__.py
pika/amqp_object.py
pika/callback.py
pika/channel.py
pika/compat.py
pika/connection.py
pika/credentials.py
pika/data.py
pika/exceptions.py
pika/frame.py
pika/heartbeat.py
pika/spec.py
pika/utils.py
pika/adapters/__init__.py
pika/adapters/asyncio_connection.py
pika/adapters/base_connection.py
pika/adapters/blocking_connection.py
pika/adapters/gevent_connection.py
pika/adapters/libev_connection.py
pika/adapters/select_connection.py
pika/adapters/tornado_connection.py
pika/adapters/twisted_connection.py
gevent_pika-0.2.dist-info/LICENSE
gevent_pika-0.2.dist-info/METADATA
gevent_pika-0.2.dist-info/WHEEL
gevent_pika-0.2.dist-info/top_level.txt
gevent_pika-0.2.dist-info/zip-safe
gevent_pika-0.2.dist-info/RECORD
