Metadata-Version: 2.1
Name: gevent-pika
Version: 0.2
Summary: Pika Python AMQP Client Library With Gevent Adapter Support
Home-page: https://pika.readthedocs.io
Maintainer: VOLTTRON Team
Maintainer-email: volttron@pnnl.gov
License: BSD
Platform: UNKNOWN
Classifier: Development Status :: 5 - Production/Stable
Classifier: Intended Audience :: Developers
Classifier: License :: OSI Approved :: BSD License
Classifier: Natural Language :: English
Classifier: Operating System :: OS Independent
Classifier: Programming Language :: Python :: 2.6
Classifier: Programming Language :: Python :: 2.7
Classifier: Programming Language :: Python :: 3
Classifier: Programming Language :: Python :: 3.3
Classifier: Programming Language :: Python :: 3.4
Classifier: Programming Language :: Python :: 3.5
Classifier: Programming Language :: Python :: Implementation :: CPython
Classifier: Programming Language :: Python :: Implementation :: Jython
Classifier: Programming Language :: Python :: Implementation :: PyPy
Classifier: Topic :: Communications
Classifier: Topic :: Internet
Classifier: Topic :: Software Development :: Libraries
Classifier: Topic :: Software Development :: Libraries :: Python Modules
Classifier: Topic :: System :: Networking
Provides-Extra: libev
Requires-Dist: pyev ; extra == 'libev'
Provides-Extra: tornado
Requires-Dist: tornado ; extra == 'tornado'
Provides-Extra: twisted
Requires-Dist: twisted ; extra == 'twisted'
